experimentalTreatingIsiPol/__init__.py
experimentalTreatingIsiPol/main.py
experimentalTreatingIsiPol/randomForestFilterCompressionFilter.py
experimentalTreatingIsiPol/randomForestModel.pkl
experimentalTreatingIsiPol/contactAngle/analyser.py
experimentalTreatingIsiPol/direction/__init__.py
experimentalTreatingIsiPol/docConfig/_68FM100.py
experimentalTreatingIsiPol/docConfig/_68FM100_biaxial.py
experimentalTreatingIsiPol/docConfig/__init__.py
experimentalTreatingIsiPol/docConfig/_generalMachine.py
experimentalTreatingIsiPol/docConfig/_older_machine.py
experimentalTreatingIsiPol/filters/data_anotted_compression_filter.pkl
experimentalTreatingIsiPol/filters/randomForestFilter.py
experimentalTreatingIsiPol/filters/randomForestModel_Compression.pkl
experimentalTreatingIsiPol/linearSearchMethod/__init__.py
experimentalTreatingIsiPol/standards/__init__.py
experimentaltreatingisipol-0.0.73.dist-info/METADATA
experimentaltreatingisipol-0.0.73.dist-info/WHEEL
experimentaltreatingisipol-0.0.73.dist-info/licenses/LICENSE
experimentaltreatingisipol-0.0.73.dist-info/RECORD
