Metadata-Version: 2.4
Name: experimentalTreatingIsiPol
Version: 0.0.73
Summary: Um package para auxialar no tratamento de dados
Project-URL: Homepage, https://github.com/jonastieppo/PostProcessingData
Author-email: Jonas Tieppo da Rocha <jonas.rocha@senairs.org.br>
License-File: LICENSE
Classifier: License :: OSI Approved :: MIT License
Classifier: Operating System :: OS Independent
Classifier: Programming Language :: Python :: 3
Requires-Python: >=3.9
Requires-Dist: matplotlib>=3.9
Requires-Dist: numpy>=2.1
Requires-Dist: pandas>=2.2.2
Requires-Dist: plotly>=5.24.1
Requires-Dist: reportlab>=4.2.5
Requires-Dist: scikit-learn
Requires-Dist: scipy>=1.14.0
Requires-Dist: seaborn>=0.13.0
Requires-Dist: xlrd>=2.0.1
